opencv_pattern/DICT_4X4_100.json.gz
opencv_pattern/DICT_4X4_1000.json.gz
opencv_pattern/DICT_4X4_250.json.gz
opencv_pattern/DICT_4X4_50.json.gz
opencv_pattern/DICT_5X5_100.json.gz
opencv_pattern/DICT_5X5_1000.json.gz
opencv_pattern/DICT_5X5_250.json.gz
opencv_pattern/DICT_5X5_50.json.gz
opencv_pattern/DICT_6X6_100.json.gz
opencv_pattern/DICT_6X6_1000.json.gz
opencv_pattern/DICT_6X6_250.json.gz
opencv_pattern/DICT_6X6_50.json.gz
opencv_pattern/DICT_7X7_100.json.gz
opencv_pattern/DICT_7X7_1000.json.gz
opencv_pattern/DICT_7X7_250.json.gz
opencv_pattern/DICT_7X7_50.json.gz
opencv_pattern/DICT_APRILTAG_16h5.json.gz
opencv_pattern/DICT_APRILTAG_25h9.json.gz
opencv_pattern/DICT_APRILTAG_36h10.json.gz
opencv_pattern/DICT_APRILTAG_36h11.json.gz
opencv_pattern/DICT_ARUCO_ORIGINAL.json.gz
opencv_pattern/__init__.py
opencv_pattern/gen_pattern.py
opencv_pattern/svgfig.py
opencv_pattern/test_charuco_board.py
opencv_pattern/tests_common.py
opencv_pattern-0.1.4.dist-info/licenses/LICENSE
opencv_pattern-0.1.4.dist-info/METADATA
opencv_pattern-0.1.4.dist-info/WHEEL
opencv_pattern-0.1.4.dist-info/entry_points.txt
opencv_pattern-0.1.4.dist-info/top_level.txt
opencv_pattern-0.1.4.dist-info/RECORD
