Metadata-Version: 2.4
Name: opencv_pattern
Version: 0.1.4
Summary: A simple OpenCV pattern generation python package
Author: Alfie
Project-URL: Homepage, https://github.com/alfieroddan/pattern-generation-opencv
Project-URL: Bug Tracker, https://github.com/alfieroddan/pattern-generation-opencv/issues
Classifier: Programming Language :: Python :: 3
Classifier: License :: OSI Approved :: MIT License
Classifier: Operating System :: OS Independent
Requires-Python: >=3.7
License-File: LICENSE
Requires-Dist: opencv-python
Requires-Dist: pyyaml
Requires-Dist: svglib
Requires-Dist: reportlab
Dynamic: license-file
